odoo/addons/sm_maintenance/__init__.py
odoo/addons/sm_maintenance/__manifest__.py
odoo/addons/sm_maintenance/demo_sommobilitat_config.json
odoo/addons/sm_maintenance/models/__init__.py
odoo/addons/sm_maintenance/models/models_api_services_utils.py
odoo/addons/sm_maintenance/models/models_sm_company.py
odoo/addons/sm_maintenance/models/models_sm_res_config_settings.py
odoo/addons/sm_maintenance/models/models_sm_resources.py
odoo/addons/sm_maintenance/models/models_sm_successful_actions_message.py
odoo/addons/sm_maintenance/models/models_sm_utils.py
odoo/addons/sm_maintenance/security/ir.model.access.csv
odoo/addons/sm_maintenance/views/views_res_config_settings.xml
odoo/addons/sm_maintenance/views/views_successful_action_message.xml
odoo12_addon_sm_maintenance-12.0.0.0.11.dist-info/METADATA
odoo12_addon_sm_maintenance-12.0.0.0.11.dist-info/WHEEL
odoo12_addon_sm_maintenance-12.0.0.0.11.dist-info/top_level.txt
odoo12_addon_sm_maintenance-12.0.0.0.11.dist-info/RECORD
