Metadata-Version: 2.1
Name: odoo12-addon-sm-maintenance
Version: 12.0.0.0.11
Summary: Module containing a set of sm_maintenance tasks to be executed periodically and keep database entries and sm services healthy
Home-page: https://www.sommobilitat.coop
Author: Som Mobilitat
Classifier: Programming Language :: Python
Classifier: Framework :: Odoo
Classifier: Framework :: Odoo :: 12.0
Requires-Python: >=3.5
Requires-Dist: odoo12-addon-sm-connect
Requires-Dist: odoo (<12.1dev,>=12.0a)
